LICENSE
README.md
setup.py
assets/__init__.py
cache/__init__.py
yumiko/__init__.py
yumiko/thumbnails.py
yumiko.egg-info/PKG-INFO
yumiko.egg-info/SOURCES.txt
yumiko.egg-info/dependency_links.txt
yumiko.egg-info/requires.txt
yumiko.egg-info/top_level.txt